README.md
setup.py
pyloopkit/__init__.py
pyloopkit/carb_math.py
pyloopkit/carb_status.py
pyloopkit/carb_store.py
pyloopkit/date.py
pyloopkit/dose.py
pyloopkit/dose_entry.py
pyloopkit/dose_math.py
pyloopkit/dose_store.py
pyloopkit/exponential_insulin_model.py
pyloopkit/generate_graphs.py
pyloopkit/glucose_math.py
pyloopkit/glucose_store.py
pyloopkit/input_validation_tools.py
pyloopkit/insulin_math.py
pyloopkit/loop_data_manager.py
pyloopkit/loop_math.py
pyloopkit/pyloop_parser.py
pyloopkit/walsh_insulin_model.py
pyloopkit_test.egg-info/PKG-INFO
pyloopkit_test.egg-info/SOURCES.txt
pyloopkit_test.egg-info/dependency_links.txt
pyloopkit_test.egg-info/requires.txt
pyloopkit_test.egg-info/top_level.txt
tests/__init__.py
tests/generate_test_fixtures.py
tests/loop_kit_tests.py
tests/path_grabber.py
tests/test_carb_math.py
tests/test_data_store.py
tests/test_dose_math.py
tests/test_glucose_math.py
tests/test_insulin_math.py
tests/test_loop_data_manager.py
tests/test_loop_math.py
tests/test_ns_date.py