Metadata-Version: 2.1
Name: pyloopkit-test
Version: 0.0.15
Summary: Python implementation of the Loop algorithm
Home-page: https://github.com/tidepool-org/PyLoopKit
Author: Tidepool
Author-email: ed@tidepool.org
License: UNKNOWN
Platform: UNKNOWN
Classifier: Development Status :: 3 - Alpha
Classifier: Intended Audience :: Developers
Classifier: License :: OSI Approved :: BSD License
Classifier: Programming Language :: Python :: 3.7
Classifier: Programming Language :: Python :: 3.6
Requires-Python: >=3.6
